thorcam/__init__.py
thorcam/camera.py
thorcam/camera_dot_net.py
thorcam-0.1.7.data/data/share/thorcam/bin/Thorlabs.TSI.ColorInterfaces.dll
thorcam-0.1.7.data/data/share/thorcam/bin/Thorlabs.TSI.ColorProcessor.dll
thorcam-0.1.7.data/data/share/thorcam/bin/Thorlabs.TSI.Core.dll
thorcam-0.1.7.data/data/share/thorcam/bin/Thorlabs.TSI.CoreInterfaces.dll
thorcam-0.1.7.data/data/share/thorcam/bin/Thorlabs.TSI.Demosaicker.dll
thorcam-0.1.7.data/data/share/thorcam/bin/Thorlabs.TSI.ImageData.dll
thorcam-0.1.7.data/data/share/thorcam/bin/Thorlabs.TSI.ImageDataInterfaces.dll
thorcam-0.1.7.data/data/share/thorcam/bin/Thorlabs.TSI.PolarizationInterfaces.dll
thorcam-0.1.7.data/data/share/thorcam/bin/Thorlabs.TSI.PolarizationProcessor.dll
thorcam-0.1.7.data/data/share/thorcam/bin/Thorlabs.TSI.TLCamera.dll
thorcam-0.1.7.data/data/share/thorcam/bin/Thorlabs.TSI.TLCameraInterfaces.dll
thorcam-0.1.7.data/data/share/thorcam/bin/pdvlib.dll
thorcam-0.1.7.data/data/share/thorcam/bin/thorlabs_ccd_edt_camera_link.dll
thorcam-0.1.7.data/data/share/thorcam/bin/thorlabs_ccd_fenrir.dll
thorcam-0.1.7.data/data/share/thorcam/bin/thorlabs_ccd_pleora_ebus.dll
thorcam-0.1.7.data/data/share/thorcam/bin/thorlabs_ccd_tsi_sdk.dll
thorcam-0.1.7.data/data/share/thorcam/bin/thorlabs_ccd_tsi_usb.dll
thorcam-0.1.7.data/data/share/thorcam/bin/thorlabs_tsi_LUT.dll
thorcam-0.1.7.data/data/share/thorcam/bin/thorlabs_tsi_camera_sdk.dll
thorcam-0.1.7.data/data/share/thorcam/bin/thorlabs_tsi_camera_sdk1_cli.dll
thorcam-0.1.7.data/data/share/thorcam/bin/thorlabs_tsi_color_processing.dll
thorcam-0.1.7.data/data/share/thorcam/bin/thorlabs_tsi_color_processing_vector_avx2.dll
thorcam-0.1.7.data/data/share/thorcam/bin/thorlabs_tsi_core_cli.dll
thorcam-0.1.7.data/data/share/thorcam/bin/thorlabs_tsi_demosaic.dll
thorcam-0.1.7.data/data/share/thorcam/bin/thorlabs_tsi_demosaic_vector_avx2.dll
thorcam-0.1.7.data/data/share/thorcam/bin/thorlabs_tsi_logger.cfg
thorcam-0.1.7.data/data/share/thorcam/bin/thorlabs_tsi_loggerx.dll
thorcam-0.1.7.dist-info/LICENSE
thorcam-0.1.7.dist-info/METADATA
thorcam-0.1.7.dist-info/WHEEL
thorcam-0.1.7.dist-info/top_level.txt
thorcam-0.1.7.dist-info/RECORD
