Metadata-Version: 2.1
Name: thorcam
Version: 0.1.7
Summary: Python interface to the .NET Thor cameras.
Home-page: https://github.com/matham/thorcam
Author: Matthew Einhorn
Author-email: matt@einhorn.dev
License: MIT
Project-URL: Bug Reports, https://github.com/matham/thorcam/issues
Project-URL: Source, https://github.com/matham/thorcam
Classifier: Development Status :: 4 - Beta
Classifier: Intended Audience :: Developers
Classifier: Topic :: Software Development :: Libraries
Classifier: License :: OSI Approved :: MIT License
Classifier: Programming Language :: Python :: 3.7
Classifier: Programming Language :: Python :: 3.8
Classifier: Programming Language :: Python :: 3.9
Classifier: Programming Language :: Python :: 3.10
License-File: LICENSE
